{
  "definitions": {
    "AuthResponse": {
      "description": "Resposta contendo o token JWT",
      "example": {
        "token": "eyJhbGciOiJIUzUxMiIsInR5cCI6IkpXVCJ9..."
      },
      "properties": {
        "token": {
          "description": "Token JWT para autenticação",
          "type": "string"
        }
      },
      "required": [
        "token"
      ],
      "title": "Resposta de Autenticação",
      "type": "object"
    },
    "SaldoResponse": {
      "description": "Detalhes do saldo da carteira solicitada",
      "example": {
        "conta_numero": "123456",
        "saldo": 1.0e3,
        "saldo_disponivel": 1.0e3,
        "saldo_reservado": 0.0,
        "tipo_carteira": "food",
        "titular": "João Silva"
      },
      "properties": {
        "conta_numero": {
          "description": "Número da conta",
          "type": "string"
        },
        "saldo": {
          "description": "Saldo disponível",
          "format": "float",
          "type": "number"
        },
        "saldo_disponivel": {
          "description": "Saldo total disponível (saldo - saldo_reservado)",
          "format": "float",
          "type": "number"
        },
        "saldo_reservado": {
          "description": "Saldo reservado",
          "format": "float",
          "type": "number"
        },
        "tipo_carteira": {
          "description": "Tipo da carteira (food, meal, cash)",
          "type": "string"
        },
        "titular": {
          "description": "Nome do titular da conta",
          "type": "string"
        }
      },
      "required": [
        "saldo_disponivel",
        "saldo_reservado",
        "saldo",
        "tipo_carteira",
        "titular",
        "conta_numero"
      ],
      "title": "Resposta de Consulta de Saldo",
      "type": "object"
    },
    "TransacaoParams": {
      "description": "Parâmetros necessários para efetuar uma transação",
      "example": {
        "conta": "123456",
        "estabelecimento": "Supermercado A",
        "mcc": "5411",
        "valor": 100.0
      },
      "properties": {
        "conta": {
          "description": "Número da conta",
          "type": "string"
        },
        "estabelecimento": {
          "description": "Nome do estabelecimento",
          "type": "string"
        },
        "mcc": {
          "description": "Código MCC do estabelecimento",
          "type": "string"
        },
        "valor": {
          "description": "Valor da transação",
          "format": "float",
          "type": "number"
        }
      },
      "required": [
        "estabelecimento",
        "mcc",
        "valor",
        "conta"
      ],
      "title": "Parâmetros da Transação",
      "type": "object"
    },
    "TransacaoResponse": {
      "description": "Resposta da transação com o código de retorno",
      "example": {
        "code": "00"
      },
      "properties": {
        "code": {
          "description": "Código de resposta (00=Aprovada, 51=Saldo insuficiente, 07=Erro)",
          "type": "string"
        }
      },
      "required": [
        "code"
      ],
      "title": "Resposta da Transação",
      "type": "object"
    }
  },
  "host": "localhost:4000",
  "info": {
    "contact": {
      "email": "xxx@xxx.com.br",
      "name": "xxxx xxx"
    },
    "description": "API para processamento de transações financeiras com diferentes tipos de carteiras.",
    "termsOfService": "https://www.escrevendocodigos.com/termos",
    "title": "API Caju",
    "version": "1.0"
  },
  "paths": {
    "/api/consultar/saldo": {
      "get": {
        "description": "Retorna o saldo atual da carteira especificada para a conta informada.\n\nExemplos de requisições:\n\n1. Consulta de saldo de carteira food:\n   GET /api/consultar/saldo?conta=123456&tipo_carteira=food\n\n2. Consulta de saldo de carteira meal:\n   GET /api/consultar/saldo?conta=789012&tipo_carteira=meal\n\n3. Consulta de saldo de carteira cash:\n   GET /api/consultar/saldo?conta=789012&tipo_carteira=cash\n",
        "operationId": "CajuWeb.SaldoController.consultar_saldo",
        "parameters": [
          {
            "description": "Número da conta",
            "in": "query",
            "name": "conta",
            "required": true,
            "type": "string"
          },
          {
            "description": "Tipo da carteira (food, meal, cash)",
            "in": "query",
            "name": "tipo_carteira",
            "required": true,
            "type": "string"
          }
        ],
        "responses": {
          "200": {
            "description": "Saldo consultado com sucesso",
            "schema": {
              "$ref": "#/definitions/SaldoResponse"
            }
          },
          "400": {
            "description": "Tipo de carteira inválido"
          },
          "401": {
            "description": "Não autorizado"
          },
          "404": {
            "description": "Conta ou carteira não encontrada"
          }
        },
        "security": [
          {
            "Bearer": []
          }
        ],
        "summary": "Consulta o saldo de uma conta e carteira específica",
        "tags": [
          "Saldo"
        ]
      }
    },
    "/api/efetivar/transacao": {
      "post": {
        "consumes": [
          "application/json"
        ],
        "description": "Processa uma transação financeira usando o número da conta, valor, código MCC e nome do estabelecimento.\n\nExemplos de requisições:\n\n1. Aprovação com carteira de alimentação:\n   { \"conta\": \"123456\", \"valor\": 100.00, \"mcc\": \"5411\", \"estabelecimento\": \"Supermercado A\" }\n\n2. Aprovação com carteira de refeição:\n   { \"conta\": \"789012\", \"valor\": 100.00, \"mcc\": \"5811\", \"estabelecimento\": \"Restaurante A\" }\n\n3. Aprovação com carteira cash (MCC não mapeado):\n   { \"conta\": \"789012\", \"valor\": 100.00, \"mcc\": \"58191\", \"estabelecimento\": \"Loja jp\" }\n\n4. Rejeição por saldo insuficiente:\n   { \"conta\": \"789012\", \"valor\": 2900.00, \"mcc\": \"581911\", \"estabelecimento\": \"Restaurante A\" }\n\n5. Sem saldo na carteira Meal, usando Cash:\n   { \"conta\": \"789012\", \"valor\": 2800.01, \"mcc\": \"5811\", \"estabelecimento\": \"Supermercado B\" }\n\n6. Mapear por estabelecimento:\n   { \"conta\": \"789012\", \"valor\": 0.55, \"mcc\": \"581911\", \"estabelecimento\": \"Restaurante A\" }\n\n7. Erro quando conta inexistente:\n   { \"conta\": \"78901200\", \"valor\": 2900, \"mcc\": \"581911\", \"estabelecimento\": \"Restaurante A\" }\n\n8. Efetivar Transação - MCC iguais:\n   { \"conta\": \"789012\", \"valor\": 0.55, \"mcc\": \"1\", \"estabelecimento\": \"padaria 1\" }\n\n9. Efetivar Transação - MCC iguais:\n   { \"conta\": \"789012\", \"valor\": 0.55, \"mcc\": \"1\", \"estabelecimento\": \"padaria 1\" }\n\n10. Efetivar Transação - MCC iguais:\n   { \"conta\": \"789012\", \"valor\": 0.55, \"mcc\": \"1\", \"estabelecimento\": \"padaria 2\" }\n\n11. Efetivar Transação - MCC iguais:\n   { \"conta\": \"789012\", \"valor\": 0.55, \"mcc\": \"1\", \"estabelecimento\": \"padaria 3\" }\n",
        "operationId": "CajuWeb.TransacaoController.efetivar_transacao",
        "parameters": [
          {
            "description": "Parâmetros da transação",
            "in": "body",
            "name": "body",
            "required": true,
            "schema": {
              "$ref": "#/definitions/TransacaoParams"
            }
          }
        ],
        "produces": [
          "application/json"
        ],
        "responses": {
          "200": {
            "description": "Transação processada",
            "schema": {
              "$ref": "#/definitions/TransacaoResponse"
            }
          },
          "401": {
            "description": "Não autorizado"
          }
        },
        "security": [
          {
            "Bearer": []
          }
        ],
        "summary": "Efetua uma transação financeira",
        "tags": [
          "Transacao"
        ]
      }
    },
    "/auth/login": {
      "post": {
        "description": "Autentica um estabelecimento usando UUID e senha. Retorna um token JWT com tempo de expiração de 1 minuto.\n\nExemplo de requisição:\nGET /auth/login?uuid=fa1b48ca-4eee-44db-9e6a-37cf4d58f1ea&senha=senha_secreta\n",
        "operationId": "CajuWeb.AuthController.login",
        "parameters": [
          {
            "description": "UUID do estabelecimento",
            "in": "query",
            "name": "uuid",
            "required": true,
            "type": "string"
          },
          {
            "description": "Senha do estabelecimento",
            "in": "query",
            "name": "senha",
            "required": true,
            "type": "string"
          }
        ],
        "responses": {
          "200": {
            "description": "Success",
            "schema": {
              "$ref": "#/definitions/AuthResponse"
            }
          },
          "401": {
            "description": "Credenciais inválidas"
          }
        },
        "summary": "Autenticação de estabelecimento",
        "tags": [
          "Auth"
        ]
      }
    }
  },
  "securityDefinitions": {
    "Bearer": {
      "description": "Token JWT no formato: Bearer {token}",
      "in": "header",
      "name": "Authorization",
      "type": "apiKey"
    }
  },
  "swagger": "2.0"
}